.gitignore
LICENSE
README.md
pyproject.toml
requirements.txt
setup.cfg
setup.py
clasp/__init__.py
clasp/annotation/__init__.py
clasp/annotation/clasp.py
clasp/annotation/plotting/__init__.py
clasp/annotation/plotting/utils.py
clasp/annotation/tests/__init__.py
clasp/annotation/tests/test_clasp.py
clasp/evaluation/__init__.py
clasp/evaluation/evaluation.py
clasp/transformations/__init__.py
clasp/transformations/clasp.py
clasp_segmentation.egg-info/PKG-INFO
clasp_segmentation.egg-info/SOURCES.txt
clasp_segmentation.egg-info/dependency_links.txt
clasp_segmentation.egg-info/not-zip-safe
clasp_segmentation.egg-info/requires.txt
clasp_segmentation.egg-info/top_level.txt
notebooks/segmentation_with_clasp.ipynb