Metadata-Version: 2.1
Name: clasp-segmentation
Version: 0.1.1
Summary: ClaSP - Time Series Segmentation
Home-page: https://github.com/patrickzib/clasp_segmenation
Author: patrickzib
Author-email: void@void.com
License: {'file': 'LICENSE'}
Project-URL: repository, https://github.com/patrickzib/clasp_segmenation
Keywords: machine-learning,time-series,segmentation,change-points,unsupervised
Platform: UNKNOWN
Classifier: Intended Audience :: Science/Research
Classifier: Intended Audience :: Developers
Classifier: License :: OSI Approved :: BSD License
Classifier: Programming Language :: Python
Classifier: Topic :: Software Development
Classifier: Topic :: Scientific/Engineering
Classifier: Operating System :: Microsoft :: Windows
Classifier: Operating System :: POSIX
Classifier: Operating System :: Unix
Classifier: Operating System :: MacOS
Classifier: Programming Language :: Python :: 3.7
Classifier: Programming Language :: Python :: 3.8
Classifier: Programming Language :: Python :: 3.9
Classifier: Programming Language :: Python :: 3.10
Requires-Python: >=3.7,<3.11
